defbench.py
defbench-0.2.0.dist-info/METADATA
defbench-0.2.0.dist-info/WHEEL
defbench-0.2.0.dist-info/licenses/LICENSE
defbench-0.2.0.dist-info/RECORD
