Metadata-Version: 2.4
Name: defbench
Version: 0.2.0
Summary: benchmark (time + memory) individual python functions
License: WTFPL
License-File: LICENSE
Keywords: benchmark,test,time,memory
Author: Shaun Mitchell
Author-email: shaun@shitchell.com
Requires-Python: >=3.10
Classifier: License :: Other/Proprietary License
Classifier: Operating System :: OS Independent
Classifier: Programming Language :: Python :: 3
Classifier: Programming Language :: Python :: 3.10
Classifier: Programming Language :: Python :: 3.11
Classifier: Programming Language :: Python :: 3.12
Classifier: Programming Language :: Python :: 3.13
Classifier: Programming Language :: Python :: 3.14
Requires-Dist: memory-profiler (>=0.61.0,<0.62.0)
Project-URL: Homepage, https://github.com/shitchell/defbench
